termvid/__init__.py
termvid/__main__.py
termvid/client.py
termvid/frame.py
termvid/norma.py
termvid/player.py
termvid/runner.py
termvid-0.0.4.data/scripts/termvid
termvid-0.0.4.dist-info/LICENSE
termvid-0.0.4.dist-info/METADATA
termvid-0.0.4.dist-info/WHEEL
termvid-0.0.4.dist-info/entry_points.txt
termvid-0.0.4.dist-info/top_level.txt
termvid-0.0.4.dist-info/RECORD
