Metadata-Version: 2.1
Name: termvid
Version: 0.0.4
Summary: UNKNOWN
Home-page: http://termvid.zephyr
Author: cole wilson
Author-email: cole@colewilson.xyz
License: none
Platform: UNKNOWN
Classifier: Programming Language :: Python :: 3
Requires-Python: >=3.6
License-File: LICENSE
Requires-Dist: opencv-python
Requires-Dist: blessed
